{
  "id": "7e1d9050-26a0-482f-8e73-40f4e552087a",
  "prevId": "00000000-0000-0000-0000-000000000000",
  "version": "7",
  "dialect": "postgresql",
  "tables": {
    "public.accounts": {
      "name": "accounts",
      "schema": "",
      "columns": {
        "user_id": {
          "name": "user_id",
          "type": "text",
          "primaryKey": false,
          "notNull": true
        },
        "type": {
          "name": "type",
          "type": "text",
          "primaryKey": false,
          "notNull": true
        },
        "provider": {
          "name": "provider",
          "type": "text",
          "primaryKey": false,
          "notNull": true
        },
        "provider_account_id": {
          "name": "provider_account_id",
          "type": "text",
          "primaryKey": false,
          "notNull": true
        },
        "refresh_token": {
          "name": "refresh_token",
          "type": "text",
          "primaryKey": false,
          "notNull": false
        },
        "access_token": {
          "name": "access_token",
          "type": "text",
          "primaryKey": false,
          "notNull": false
        },
        "expires_at": {
          "name": "expires_at",
          "type": "integer",
          "primaryKey": false,
          "notNull": false
        },
        "token_type": {
          "name": "token_type",
          "type": "text",
          "primaryKey": false,
          "notNull": false
        },
        "scope": {
          "name": "scope",
          "type": "text",
          "primaryKey": false,
          "notNull": false
        },
        "id_token": {
          "name": "id_token",
          "type": "text",
          "primaryKey": false,
          "notNull": false
        },
        "session_state": {
          "name": "session_state",
          "type": "text",
          "primaryKey": false,
          "notNull": false
        }
      },
      "indexes": {},
      "foreignKeys": {
        "accounts_user_id_users_id_fk": {
          "name": "accounts_user_id_users_id_fk",
          "tableFrom": "accounts",
          "tableTo": "users",
          "columnsFrom": [
            "user_id"
          ],
          "columnsTo": [
            "id"
          ],
          "onDelete": "cascade",
          "onUpdate": "no action"
        }
      },
      "compositePrimaryKeys": {
        "accounts_provider_provider_account_id_pk": {
          "name": "accounts_provider_provider_account_id_pk",
          "columns": [
            "provider",
            "provider_account_id"
          ]
        }
      },
      "uniqueConstraints": {},
      "policies": {},
      "checkConstraints": {},
      "isRLSEnabled": false
    },
    "public.api_endpoints": {
      "name": "api_endpoints",
      "schema": "",
      "columns": {
        "id": {
          "name": "id",
          "type": "text",
          "primaryKey": true,
          "notNull": true
        },
        "source_id": {
          "name": "source_id",
          "type": "text",
          "primaryKey": false,
          "notNull": true
        },
        "path": {
          "name": "path",
          "type": "text",
          "primaryKey": false,
          "notNull": true
        },
        "method": {
          "name": "method",
          "type": "text",
          "primaryKey": false,
          "notNull": true
        },
        "operation_id": {
          "name": "operation_id",
          "type": "text",
          "primaryKey": false,
          "notNull": false
        },
        "summary": {
          "name": "summary",
          "type": "text",
          "primaryKey": false,
          "notNull": false
        },
        "description": {
          "name": "description",
          "type": "text",
          "primaryKey": false,
          "notNull": false
        },
        "tags": {
          "name": "tags",
          "type": "jsonb",
          "primaryKey": false,
          "notNull": false,
          "default": "'[]'::jsonb"
        },
        "parameters": {
          "name": "parameters",
          "type": "jsonb",
          "primaryKey": false,
          "notNull": false,
          "default": "'[]'::jsonb"
        },
        "request_body": {
          "name": "request_body",
          "type": "jsonb",
          "primaryKey": false,
          "notNull": false
        },
        "responses": {
          "name": "responses",
          "type": "jsonb",
          "primaryKey": false,
          "notNull": false,
          "default": "'{}'::jsonb"
        },
        "deprecated": {
          "name": "deprecated",
          "type": "boolean",
          "primaryKey": false,
          "notNull": true,
          "default": false
        },
        "visibility": {
          "name": "visibility",
          "type": "visibility_level",
          "typeSchema": "public",
          "primaryKey": false,
          "notNull": true,
          "default": "'public'"
        },
        "document_id": {
          "name": "document_id",
          "type": "text",
          "primaryKey": false,
          "notNull": false
        },
        "created_at": {
          "name": "created_at",
          "type": "timestamp",
          "primaryKey": false,
          "notNull": true,
          "default": "now()"
        },
        "updated_at": {
          "name": "updated_at",
          "type": "timestamp",
          "primaryKey": false,
          "notNull": true,
          "default": "now()"
        }
      },
      "indexes": {
        "api_endpoints_source_id_idx": {
          "name": "api_endpoints_source_id_idx",
          "columns": [
            {
              "expression": "source_id",
              "isExpression": false,
              "asc": true,
              "nulls": "last"
            }
          ],
          "isUnique": false,
          "concurrently": false,
          "method": "btree",
          "with": {}
        },
        "api_endpoints_method_path_idx": {
          "name": "api_endpoints_method_path_idx",
          "columns": [
            {
              "expression": "method",
              "isExpression": false,
              "asc": true,
              "nulls": "last"
            },
            {
              "expression": "path",
              "isExpression": false,
              "asc": true,
              "nulls": "last"
            }
          ],
          "isUnique": false,
          "concurrently": false,
          "method": "btree",
          "with": {}
        }
      },
      "foreignKeys": {
        "api_endpoints_source_id_openapi_sources_id_fk": {
          "name": "api_endpoints_source_id_openapi_sources_id_fk",
          "tableFrom": "api_endpoints",
          "tableTo": "openapi_sources",
          "columnsFrom": [
            "source_id"
          ],
          "columnsTo": [
            "id"
          ],
          "onDelete": "cascade",
          "onUpdate": "no action"
        }
      },
      "compositePrimaryKeys": {},
      "uniqueConstraints": {},
      "policies": {},
      "checkConstraints": {},
      "isRLSEnabled": false
    },
    "public.api_versions": {
      "name": "api_versions",
      "schema": "",
      "columns": {
        "id": {
          "name": "id",
          "type": "text",
          "primaryKey": true,
          "notNull": true
        },
        "workspace_id": {
          "name": "workspace_id",
          "type": "text",
          "primaryKey": false,
          "notNull": true
        },
        "label": {
          "name": "label",
          "type": "text",
          "primaryKey": false,
          "notNull": true
        },
        "slug": {
          "name": "slug",
          "type": "text",
          "primaryKey": false,
          "notNull": true
        },
        "base_url": {
          "name": "base_url",
          "type": "text",
          "primaryKey": false,
          "notNull": false
        },
        "status": {
          "name": "status",
          "type": "api_version_status",
          "typeSchema": "public",
          "primaryKey": false,
          "notNull": true,
          "default": "'active'"
        },
        "is_default": {
          "name": "is_default",
          "type": "boolean",
          "primaryKey": false,
          "notNull": true,
          "default": false
        },
        "source_id": {
          "name": "source_id",
          "type": "text",
          "primaryKey": false,
          "notNull": false
        },
        "sort_order": {
          "name": "sort_order",
          "type": "integer",
          "primaryKey": false,
          "notNull": true,
          "default": 0
        },
        "created_at": {
          "name": "created_at",
          "type": "timestamp",
          "primaryKey": false,
          "notNull": true,
          "default": "now()"
        }
      },
      "indexes": {
        "api_versions_workspace_slug_idx": {
          "name": "api_versions_workspace_slug_idx",
          "columns": [
            {
              "expression": "workspace_id",
              "isExpression": false,
              "asc": true,
              "nulls": "last"
            },
            {
              "expression": "slug",
              "isExpression": false,
              "asc": true,
              "nulls": "last"
            }
          ],
          "isUnique": true,
          "concurrently": false,
          "method": "btree",
          "with": {}
        },
        "api_versions_workspace_id_idx": {
          "name": "api_versions_workspace_id_idx",
          "columns": [
            {
              "expression": "workspace_id",
              "isExpression": false,
              "asc": true,
              "nulls": "last"
            }
          ],
          "isUnique": false,
          "concurrently": false,
          "method": "btree",
          "with": {}
        }
      },
      "foreignKeys": {
        "api_versions_workspace_id_workspaces_id_fk": {
          "name": "api_versions_workspace_id_workspaces_id_fk",
          "tableFrom": "api_versions",
          "tableTo": "workspaces",
          "columnsFrom": [
            "workspace_id"
          ],
          "columnsTo": [
            "id"
          ],
          "onDelete": "cascade",
          "onUpdate": "no action"
        }
      },
      "compositePrimaryKeys": {},
      "uniqueConstraints": {},
      "policies": {},
      "checkConstraints": {},
      "isRLSEnabled": false
    },
    "public.doc_snippets": {
      "name": "doc_snippets",
      "schema": "",
      "columns": {
        "workspace_id": {
          "name": "workspace_id",
          "type": "text",
          "primaryKey": false,
          "notNull": true
        },
        "id": {
          "name": "id",
          "type": "text",
          "primaryKey": false,
          "notNull": true
        },
        "label": {
          "name": "label",
          "type": "text",
          "primaryKey": false,
          "notNull": true
        },
        "description": {
          "name": "description",
          "type": "text",
          "primaryKey": false,
          "notNull": true
        },
        "category": {
          "name": "category",
          "type": "doc_snippet_category",
          "typeSchema": "public",
          "primaryKey": false,
          "notNull": true
        },
        "keywords": {
          "name": "keywords",
          "type": "text[]",
          "primaryKey": false,
          "notNull": true
        },
        "template": {
          "name": "template",
          "type": "text",
          "primaryKey": false,
          "notNull": true
        },
        "sort_order": {
          "name": "sort_order",
          "type": "integer",
          "primaryKey": false,
          "notNull": true,
          "default": 0
        },
        "created_at": {
          "name": "created_at",
          "type": "timestamp",
          "primaryKey": false,
          "notNull": true,
          "default": "now()"
        },
        "updated_at": {
          "name": "updated_at",
          "type": "timestamp",
          "primaryKey": false,
          "notNull": true,
          "default": "now()"
        }
      },
      "indexes": {
        "doc_snippets_workspace_id_idx": {
          "name": "doc_snippets_workspace_id_idx",
          "columns": [
            {
              "expression": "workspace_id",
              "isExpression": false,
              "asc": true,
              "nulls": "last"
            }
          ],
          "isUnique": false,
          "concurrently": false,
          "method": "btree",
          "with": {}
        },
        "doc_snippets_category_idx": {
          "name": "doc_snippets_category_idx",
          "columns": [
            {
              "expression": "category",
              "isExpression": false,
              "asc": true,
              "nulls": "last"
            }
          ],
          "isUnique": false,
          "concurrently": false,
          "method": "btree",
          "with": {}
        }
      },
      "foreignKeys": {
        "doc_snippets_workspace_id_workspaces_id_fk": {
          "name": "doc_snippets_workspace_id_workspaces_id_fk",
          "tableFrom": "doc_snippets",
          "tableTo": "workspaces",
          "columnsFrom": [
            "workspace_id"
          ],
          "columnsTo": [
            "id"
          ],
          "onDelete": "cascade",
          "onUpdate": "no action"
        }
      },
      "compositePrimaryKeys": {
        "doc_snippets_workspace_id_id_pk": {
          "name": "doc_snippets_workspace_id_id_pk",
          "columns": [
            "workspace_id",
            "id"
          ]
        }
      },
      "uniqueConstraints": {},
      "policies": {},
      "checkConstraints": {},
      "isRLSEnabled": false
    },
    "public.document_feedback": {
      "name": "document_feedback",
      "schema": "",
      "columns": {
        "id": {
          "name": "id",
          "type": "text",
          "primaryKey": true,
          "notNull": true
        },
        "document_id": {
          "name": "document_id",
          "type": "text",
          "primaryKey": false,
          "notNull": true
        },
        "user_id": {
          "name": "user_id",
          "type": "text",
          "primaryKey": false,
          "notNull": false
        },
        "is_helpful": {
          "name": "is_helpful",
          "type": "boolean",
          "primaryKey": false,
          "notNull": true
        },
        "comment": {
          "name": "comment",
          "type": "text",
          "primaryKey": false,
          "notNull": false
        },
        "created_at": {
          "name": "created_at",
          "type": "timestamp",
          "primaryKey": false,
          "notNull": true,
          "default": "now()"
        }
      },
      "indexes": {
        "document_feedback_document_id_idx": {
          "name": "document_feedback_document_id_idx",
          "columns": [
            {
              "expression": "document_id",
              "isExpression": false,
              "asc": true,
              "nulls": "last"
            }
          ],
          "isUnique": false,
          "concurrently": false,
          "method": "btree",
          "with": {}
        }
      },
      "foreignKeys": {
        "document_feedback_document_id_documents_id_fk": {
          "name": "document_feedback_document_id_documents_id_fk",
          "tableFrom": "document_feedback",
          "tableTo": "documents",
          "columnsFrom": [
            "document_id"
          ],
          "columnsTo": [
            "id"
          ],
          "onDelete": "cascade",
          "onUpdate": "no action"
        }
      },
      "compositePrimaryKeys": {},
      "uniqueConstraints": {},
      "policies": {},
      "checkConstraints": {},
      "isRLSEnabled": false
    },
    "public.document_versions": {
      "name": "document_versions",
      "schema": "",
      "columns": {
        "id": {
          "name": "id",
          "type": "text",
          "primaryKey": true,
          "notNull": true
        },
        "document_id": {
          "name": "document_id",
          "type": "text",
          "primaryKey": false,
          "notNull": true
        },
        "content": {
          "name": "content",
          "type": "text",
          "primaryKey": false,
          "notNull": true
        },
        "word_count": {
          "name": "word_count",
          "type": "integer",
          "primaryKey": false,
          "notNull": true,
          "default": 0
        },
        "saved_at": {
          "name": "saved_at",
          "type": "timestamp",
          "primaryKey": false,
          "notNull": true,
          "default": "now()"
        }
      },
      "indexes": {
        "document_versions_document_id_idx": {
          "name": "document_versions_document_id_idx",
          "columns": [
            {
              "expression": "document_id",
              "isExpression": false,
              "asc": true,
              "nulls": "last"
            }
          ],
          "isUnique": false,
          "concurrently": false,
          "method": "btree",
          "with": {}
        }
      },
      "foreignKeys": {
        "document_versions_document_id_documents_id_fk": {
          "name": "document_versions_document_id_documents_id_fk",
          "tableFrom": "document_versions",
          "tableTo": "documents",
          "columnsFrom": [
            "document_id"
          ],
          "columnsTo": [
            "id"
          ],
          "onDelete": "cascade",
          "onUpdate": "no action"
        }
      },
      "compositePrimaryKeys": {},
      "uniqueConstraints": {},
      "policies": {},
      "checkConstraints": {},
      "isRLSEnabled": false
    },
    "public.documents": {
      "name": "documents",
      "schema": "",
      "columns": {
        "id": {
          "name": "id",
          "type": "text",
          "primaryKey": true,
          "notNull": true
        },
        "workspace_id": {
          "name": "workspace_id",
          "type": "text",
          "primaryKey": false,
          "notNull": true
        },
        "title": {
          "name": "title",
          "type": "text",
          "primaryKey": false,
          "notNull": true,
          "default": "'Untitled'"
        },
        "content": {
          "name": "content",
          "type": "text",
          "primaryKey": false,
          "notNull": true,
          "default": "''"
        },
        "summary": {
          "name": "summary",
          "type": "text",
          "primaryKey": false,
          "notNull": true,
          "default": "''"
        },
        "status": {
          "name": "status",
          "type": "doc_status",
          "typeSchema": "public",
          "primaryKey": false,
          "notNull": true,
          "default": "'draft'"
        },
        "visibility": {
          "name": "visibility",
          "type": "visibility_level",
          "typeSchema": "public",
          "primaryKey": false,
          "notNull": true,
          "default": "'public'"
        },
        "api_version_id": {
          "name": "api_version_id",
          "type": "text",
          "primaryKey": false,
          "notNull": false
        },
        "created_at": {
          "name": "created_at",
          "type": "timestamp",
          "primaryKey": false,
          "notNull": true,
          "default": "now()"
        },
        "updated_at": {
          "name": "updated_at",
          "type": "timestamp",
          "primaryKey": false,
          "notNull": true,
          "default": "now()"
        },
        "created_by": {
          "name": "created_by",
          "type": "text",
          "primaryKey": false,
          "notNull": false
        }
      },
      "indexes": {
        "documents_workspace_id_idx": {
          "name": "documents_workspace_id_idx",
          "columns": [
            {
              "expression": "workspace_id",
              "isExpression": false,
              "asc": true,
              "nulls": "last"
            }
          ],
          "isUnique": false,
          "concurrently": false,
          "method": "btree",
          "with": {}
        },
        "documents_status_idx": {
          "name": "documents_status_idx",
          "columns": [
            {
              "expression": "status",
              "isExpression": false,
              "asc": true,
              "nulls": "last"
            }
          ],
          "isUnique": false,
          "concurrently": false,
          "method": "btree",
          "with": {}
        },
        "documents_created_by_idx": {
          "name": "documents_created_by_idx",
          "columns": [
            {
              "expression": "created_by",
              "isExpression": false,
              "asc": true,
              "nulls": "last"
            }
          ],
          "isUnique": false,
          "concurrently": false,
          "method": "btree",
          "with": {}
        },
        "documents_api_version_id_idx": {
          "name": "documents_api_version_id_idx",
          "columns": [
            {
              "expression": "api_version_id",
              "isExpression": false,
              "asc": true,
              "nulls": "last"
            }
          ],
          "isUnique": false,
          "concurrently": false,
          "method": "btree",
          "with": {}
        }
      },
      "foreignKeys": {
        "documents_workspace_id_workspaces_id_fk": {
          "name": "documents_workspace_id_workspaces_id_fk",
          "tableFrom": "documents",
          "tableTo": "workspaces",
          "columnsFrom": [
            "workspace_id"
          ],
          "columnsTo": [
            "id"
          ],
          "onDelete": "cascade",
          "onUpdate": "no action"
        },
        "documents_created_by_users_id_fk": {
          "name": "documents_created_by_users_id_fk",
          "tableFrom": "documents",
          "tableTo": "users",
          "columnsFrom": [
            "created_by"
          ],
          "columnsTo": [
            "id"
          ],
          "onDelete": "set null",
          "onUpdate": "no action"
        }
      },
      "compositePrimaryKeys": {},
      "uniqueConstraints": {},
      "policies": {},
      "checkConstraints": {},
      "isRLSEnabled": false
    },
    "public.inline_comments": {
      "name": "inline_comments",
      "schema": "",
      "columns": {
        "id": {
          "name": "id",
          "type": "text",
          "primaryKey": true,
          "notNull": true
        },
        "document_id": {
          "name": "document_id",
          "type": "text",
          "primaryKey": false,
          "notNull": true
        },
        "author_id": {
          "name": "author_id",
          "type": "text",
          "primaryKey": false,
          "notNull": true
        },
        "anchor_type": {
          "name": "anchor_type",
          "type": "text",
          "primaryKey": false,
          "notNull": true
        },
        "anchor_from": {
          "name": "anchor_from",
          "type": "integer",
          "primaryKey": false,
          "notNull": false
        },
        "anchor_to": {
          "name": "anchor_to",
          "type": "integer",
          "primaryKey": false,
          "notNull": false
        },
        "anchor_block_id": {
          "name": "anchor_block_id",
          "type": "text",
          "primaryKey": false,
          "notNull": false
        },
        "quoted_text": {
          "name": "quoted_text",
          "type": "text",
          "primaryKey": false,
          "notNull": false
        },
        "body": {
          "name": "body",
          "type": "text",
          "primaryKey": false,
          "notNull": true
        },
        "parent_id": {
          "name": "parent_id",
          "type": "text",
          "primaryKey": false,
          "notNull": false
        },
        "thread_resolved": {
          "name": "thread_resolved",
          "type": "boolean",
          "primaryKey": false,
          "notNull": true,
          "default": false
        },
        "resolved_by": {
          "name": "resolved_by",
          "type": "text",
          "primaryKey": false,
          "notNull": false
        },
        "resolved_at": {
          "name": "resolved_at",
          "type": "timestamp",
          "primaryKey": false,
          "notNull": false
        },
        "created_at": {
          "name": "created_at",
          "type": "timestamp",
          "primaryKey": false,
          "notNull": true,
          "default": "now()"
        },
        "updated_at": {
          "name": "updated_at",
          "type": "timestamp",
          "primaryKey": false,
          "notNull": true,
          "default": "now()"
        }
      },
      "indexes": {
        "inline_comments_document_id_idx": {
          "name": "inline_comments_document_id_idx",
          "columns": [
            {
              "expression": "document_id",
              "isExpression": false,
              "asc": true,
              "nulls": "last"
            }
          ],
          "isUnique": false,
          "concurrently": false,
          "method": "btree",
          "with": {}
        },
        "inline_comments_parent_id_idx": {
          "name": "inline_comments_parent_id_idx",
          "columns": [
            {
              "expression": "parent_id",
              "isExpression": false,
              "asc": true,
              "nulls": "last"
            }
          ],
          "isUnique": false,
          "concurrently": false,
          "method": "btree",
          "with": {}
        }
      },
      "foreignKeys": {
        "inline_comments_document_id_documents_id_fk": {
          "name": "inline_comments_document_id_documents_id_fk",
          "tableFrom": "inline_comments",
          "tableTo": "documents",
          "columnsFrom": [
            "document_id"
          ],
          "columnsTo": [
            "id"
          ],
          "onDelete": "cascade",
          "onUpdate": "no action"
        },
        "inline_comments_author_id_users_id_fk": {
          "name": "inline_comments_author_id_users_id_fk",
          "tableFrom": "inline_comments",
          "tableTo": "users",
          "columnsFrom": [
            "author_id"
          ],
          "columnsTo": [
            "id"
          ],
          "onDelete": "cascade",
          "onUpdate": "no action"
        }
      },
      "compositePrimaryKeys": {},
      "uniqueConstraints": {},
      "policies": {},
      "checkConstraints": {},
      "isRLSEnabled": false
    },
    "public.link_checks": {
      "name": "link_checks",
      "schema": "",
      "columns": {
        "id": {
          "name": "id",
          "type": "text",
          "primaryKey": true,
          "notNull": true
        },
        "workspace_id": {
          "name": "workspace_id",
          "type": "text",
          "primaryKey": false,
          "notNull": true
        },
        "document_id": {
          "name": "document_id",
          "type": "text",
          "primaryKey": false,
          "notNull": true
        },
        "url": {
          "name": "url",
          "type": "text",
          "primaryKey": false,
          "notNull": true
        },
        "status_code": {
          "name": "status_code",
          "type": "integer",
          "primaryKey": false,
          "notNull": false
        },
        "is_alive": {
          "name": "is_alive",
          "type": "boolean",
          "primaryKey": false,
          "notNull": false
        },
        "error_message": {
          "name": "error_message",
          "type": "text",
          "primaryKey": false,
          "notNull": false
        },
        "last_checked_at": {
          "name": "last_checked_at",
          "type": "timestamp",
          "primaryKey": false,
          "notNull": true,
          "default": "now()"
        }
      },
      "indexes": {
        "link_checks_document_url_idx": {
          "name": "link_checks_document_url_idx",
          "columns": [
            {
              "expression": "document_id",
              "isExpression": false,
              "asc": true,
              "nulls": "last"
            },
            {
              "expression": "url",
              "isExpression": false,
              "asc": true,
              "nulls": "last"
            }
          ],
          "isUnique": true,
          "concurrently": false,
          "method": "btree",
          "with": {}
        },
        "link_checks_workspace_id_idx": {
          "name": "link_checks_workspace_id_idx",
          "columns": [
            {
              "expression": "workspace_id",
              "isExpression": false,
              "asc": true,
              "nulls": "last"
            }
          ],
          "isUnique": false,
          "concurrently": false,
          "method": "btree",
          "with": {}
        }
      },
      "foreignKeys": {
        "link_checks_document_id_documents_id_fk": {
          "name": "link_checks_document_id_documents_id_fk",
          "tableFrom": "link_checks",
          "tableTo": "documents",
          "columnsFrom": [
            "document_id"
          ],
          "columnsTo": [
            "id"
          ],
          "onDelete": "cascade",
          "onUpdate": "no action"
        }
      },
      "compositePrimaryKeys": {},
      "uniqueConstraints": {},
      "policies": {},
      "checkConstraints": {},
      "isRLSEnabled": false
    },
    "public.openapi_snapshots": {
      "name": "openapi_snapshots",
      "schema": "",
      "columns": {
        "id": {
          "name": "id",
          "type": "text",
          "primaryKey": true,
          "notNull": true
        },
        "source_id": {
          "name": "source_id",
          "type": "text",
          "primaryKey": false,
          "notNull": true
        },
        "raw_content": {
          "name": "raw_content",
          "type": "text",
          "primaryKey": false,
          "notNull": true
        },
        "parsed_version": {
          "name": "parsed_version",
          "type": "text",
          "primaryKey": false,
          "notNull": false
        },
        "checksum": {
          "name": "checksum",
          "type": "text",
          "primaryKey": false,
          "notNull": true
        },
        "snapshot_at": {
          "name": "snapshot_at",
          "type": "timestamp",
          "primaryKey": false,
          "notNull": true,
          "default": "now()"
        }
      },
      "indexes": {
        "openapi_snapshots_source_id_idx": {
          "name": "openapi_snapshots_source_id_idx",
          "columns": [
            {
              "expression": "source_id",
              "isExpression": false,
              "asc": true,
              "nulls": "last"
            }
          ],
          "isUnique": false,
          "concurrently": false,
          "method": "btree",
          "with": {}
        }
      },
      "foreignKeys": {
        "openapi_snapshots_source_id_openapi_sources_id_fk": {
          "name": "openapi_snapshots_source_id_openapi_sources_id_fk",
          "tableFrom": "openapi_snapshots",
          "tableTo": "openapi_sources",
          "columnsFrom": [
            "source_id"
          ],
          "columnsTo": [
            "id"
          ],
          "onDelete": "cascade",
          "onUpdate": "no action"
        }
      },
      "compositePrimaryKeys": {},
      "uniqueConstraints": {},
      "policies": {},
      "checkConstraints": {},
      "isRLSEnabled": false
    },
    "public.openapi_sources": {
      "name": "openapi_sources",
      "schema": "",
      "columns": {
        "id": {
          "name": "id",
          "type": "text",
          "primaryKey": true,
          "notNull": true
        },
        "workspace_id": {
          "name": "workspace_id",
          "type": "text",
          "primaryKey": false,
          "notNull": true
        },
        "name": {
          "name": "name",
          "type": "text",
          "primaryKey": false,
          "notNull": true
        },
        "source_type": {
          "name": "source_type",
          "type": "openapi_source_type",
          "typeSchema": "public",
          "primaryKey": false,
          "notNull": true
        },
        "source_url": {
          "name": "source_url",
          "type": "text",
          "primaryKey": false,
          "notNull": false
        },
        "raw_content": {
          "name": "raw_content",
          "type": "text",
          "primaryKey": false,
          "notNull": true
        },
        "parsed_version": {
          "name": "parsed_version",
          "type": "text",
          "primaryKey": false,
          "notNull": false
        },
        "openapi_version": {
          "name": "openapi_version",
          "type": "text",
          "primaryKey": false,
          "notNull": false
        },
        "checksum": {
          "name": "checksum",
          "type": "text",
          "primaryKey": false,
          "notNull": true
        },
        "last_synced_at": {
          "name": "last_synced_at",
          "type": "timestamp",
          "primaryKey": false,
          "notNull": true,
          "default": "now()"
        },
        "created_at": {
          "name": "created_at",
          "type": "timestamp",
          "primaryKey": false,
          "notNull": true,
          "default": "now()"
        }
      },
      "indexes": {
        "openapi_sources_workspace_id_idx": {
          "name": "openapi_sources_workspace_id_idx",
          "columns": [
            {
              "expression": "workspace_id",
              "isExpression": false,
              "asc": true,
              "nulls": "last"
            }
          ],
          "isUnique": false,
          "concurrently": false,
          "method": "btree",
          "with": {}
        }
      },
      "foreignKeys": {
        "openapi_sources_workspace_id_workspaces_id_fk": {
          "name": "openapi_sources_workspace_id_workspaces_id_fk",
          "tableFrom": "openapi_sources",
          "tableTo": "workspaces",
          "columnsFrom": [
            "workspace_id"
          ],
          "columnsTo": [
            "id"
          ],
          "onDelete": "cascade",
          "onUpdate": "no action"
        }
      },
      "compositePrimaryKeys": {},
      "uniqueConstraints": {},
      "policies": {},
      "checkConstraints": {},
      "isRLSEnabled": false
    },
    "public.partner_group_members": {
      "name": "partner_group_members",
      "schema": "",
      "columns": {
        "group_id": {
          "name": "group_id",
          "type": "text",
          "primaryKey": false,
          "notNull": true
        },
        "user_id": {
          "name": "user_id",
          "type": "text",
          "primaryKey": false,
          "notNull": true
        }
      },
      "indexes": {},
      "foreignKeys": {
        "partner_group_members_group_id_partner_groups_id_fk": {
          "name": "partner_group_members_group_id_partner_groups_id_fk",
          "tableFrom": "partner_group_members",
          "tableTo": "partner_groups",
          "columnsFrom": [
            "group_id"
          ],
          "columnsTo": [
            "id"
          ],
          "onDelete": "cascade",
          "onUpdate": "no action"
        },
        "partner_group_members_user_id_users_id_fk": {
          "name": "partner_group_members_user_id_users_id_fk",
          "tableFrom": "partner_group_members",
          "tableTo": "users",
          "columnsFrom": [
            "user_id"
          ],
          "columnsTo": [
            "id"
          ],
          "onDelete": "cascade",
          "onUpdate": "no action"
        }
      },
      "compositePrimaryKeys": {
        "partner_group_members_group_id_user_id_pk": {
          "name": "partner_group_members_group_id_user_id_pk",
          "columns": [
            "group_id",
            "user_id"
          ]
        }
      },
      "uniqueConstraints": {},
      "policies": {},
      "checkConstraints": {},
      "isRLSEnabled": false
    },
    "public.partner_groups": {
      "name": "partner_groups",
      "schema": "",
      "columns": {
        "id": {
          "name": "id",
          "type": "text",
          "primaryKey": true,
          "notNull": true
        },
        "workspace_id": {
          "name": "workspace_id",
          "type": "text",
          "primaryKey": false,
          "notNull": true
        },
        "name": {
          "name": "name",
          "type": "text",
          "primaryKey": false,
          "notNull": true
        },
        "created_at": {
          "name": "created_at",
          "type": "timestamp",
          "primaryKey": false,
          "notNull": true,
          "default": "now()"
        }
      },
      "indexes": {
        "partner_groups_workspace_id_idx": {
          "name": "partner_groups_workspace_id_idx",
          "columns": [
            {
              "expression": "workspace_id",
              "isExpression": false,
              "asc": true,
              "nulls": "last"
            }
          ],
          "isUnique": false,
          "concurrently": false,
          "method": "btree",
          "with": {}
        }
      },
      "foreignKeys": {
        "partner_groups_workspace_id_workspaces_id_fk": {
          "name": "partner_groups_workspace_id_workspaces_id_fk",
          "tableFrom": "partner_groups",
          "tableTo": "workspaces",
          "columnsFrom": [
            "workspace_id"
          ],
          "columnsTo": [
            "id"
          ],
          "onDelete": "cascade",
          "onUpdate": "no action"
        }
      },
      "compositePrimaryKeys": {},
      "uniqueConstraints": {},
      "policies": {},
      "checkConstraints": {},
      "isRLSEnabled": false
    },
    "public.search_logs": {
      "name": "search_logs",
      "schema": "",
      "columns": {
        "id": {
          "name": "id",
          "type": "text",
          "primaryKey": true,
          "notNull": true
        },
        "workspace_id": {
          "name": "workspace_id",
          "type": "text",
          "primaryKey": false,
          "notNull": true
        },
        "user_id": {
          "name": "user_id",
          "type": "text",
          "primaryKey": false,
          "notNull": false
        },
        "query": {
          "name": "query",
          "type": "text",
          "primaryKey": false,
          "notNull": true
        },
        "result_count": {
          "name": "result_count",
          "type": "integer",
          "primaryKey": false,
          "notNull": true
        },
        "clicked_document_id": {
          "name": "clicked_document_id",
          "type": "text",
          "primaryKey": false,
          "notNull": false
        },
        "searched_at": {
          "name": "searched_at",
          "type": "timestamp",
          "primaryKey": false,
          "notNull": true,
          "default": "now()"
        }
      },
      "indexes": {
        "search_logs_workspace_id_idx": {
          "name": "search_logs_workspace_id_idx",
          "columns": [
            {
              "expression": "workspace_id",
              "isExpression": false,
              "asc": true,
              "nulls": "last"
            }
          ],
          "isUnique": false,
          "concurrently": false,
          "method": "btree",
          "with": {}
        },
        "search_logs_searched_at_idx": {
          "name": "search_logs_searched_at_idx",
          "columns": [
            {
              "expression": "searched_at",
              "isExpression": false,
              "asc": true,
              "nulls": "last"
            }
          ],
          "isUnique": false,
          "concurrently": false,
          "method": "btree",
          "with": {}
        }
      },
      "foreignKeys": {},
      "compositePrimaryKeys": {},
      "uniqueConstraints": {},
      "policies": {},
      "checkConstraints": {},
      "isRLSEnabled": false
    },
    "public.sessions": {
      "name": "sessions",
      "schema": "",
      "columns": {
        "session_token": {
          "name": "session_token",
          "type": "text",
          "primaryKey": true,
          "notNull": true
        },
        "user_id": {
          "name": "user_id",
          "type": "text",
          "primaryKey": false,
          "notNull": true
        },
        "expires": {
          "name": "expires",
          "type": "timestamp",
          "primaryKey": false,
          "notNull": true
        }
      },
      "indexes": {},
      "foreignKeys": {
        "sessions_user_id_users_id_fk": {
          "name": "sessions_user_id_users_id_fk",
          "tableFrom": "sessions",
          "tableTo": "users",
          "columnsFrom": [
            "user_id"
          ],
          "columnsTo": [
            "id"
          ],
          "onDelete": "cascade",
          "onUpdate": "no action"
        }
      },
      "compositePrimaryKeys": {},
      "uniqueConstraints": {},
      "policies": {},
      "checkConstraints": {},
      "isRLSEnabled": false
    },
    "public.users": {
      "name": "users",
      "schema": "",
      "columns": {
        "id": {
          "name": "id",
          "type": "text",
          "primaryKey": true,
          "notNull": true
        },
        "name": {
          "name": "name",
          "type": "text",
          "primaryKey": false,
          "notNull": false
        },
        "email": {
          "name": "email",
          "type": "text",
          "primaryKey": false,
          "notNull": false
        },
        "email_verified": {
          "name": "email_verified",
          "type": "timestamp",
          "primaryKey": false,
          "notNull": false
        },
        "image": {
          "name": "image",
          "type": "text",
          "primaryKey": false,
          "notNull": false
        }
      },
      "indexes": {},
      "foreignKeys": {},
      "compositePrimaryKeys": {},
      "uniqueConstraints": {
        "users_email_unique": {
          "name": "users_email_unique",
          "nullsNotDistinct": false,
          "columns": [
            "email"
          ]
        }
      },
      "policies": {},
      "checkConstraints": {},
      "isRLSEnabled": false
    },
    "public.verification_tokens": {
      "name": "verification_tokens",
      "schema": "",
      "columns": {
        "identifier": {
          "name": "identifier",
          "type": "text",
          "primaryKey": false,
          "notNull": true
        },
        "token": {
          "name": "token",
          "type": "text",
          "primaryKey": false,
          "notNull": true
        },
        "expires": {
          "name": "expires",
          "type": "timestamp",
          "primaryKey": false,
          "notNull": true
        }
      },
      "indexes": {},
      "foreignKeys": {},
      "compositePrimaryKeys": {
        "verification_tokens_identifier_token_pk": {
          "name": "verification_tokens_identifier_token_pk",
          "columns": [
            "identifier",
            "token"
          ]
        }
      },
      "uniqueConstraints": {},
      "policies": {},
      "checkConstraints": {},
      "isRLSEnabled": false
    },
    "public.workspace_members": {
      "name": "workspace_members",
      "schema": "",
      "columns": {
        "user_id": {
          "name": "user_id",
          "type": "text",
          "primaryKey": false,
          "notNull": true
        },
        "workspace_id": {
          "name": "workspace_id",
          "type": "text",
          "primaryKey": false,
          "notNull": true
        },
        "role": {
          "name": "role",
          "type": "member_role",
          "typeSchema": "public",
          "primaryKey": false,
          "notNull": true,
          "default": "'editor'"
        },
        "joined_at": {
          "name": "joined_at",
          "type": "timestamp",
          "primaryKey": false,
          "notNull": true,
          "default": "now()"
        }
      },
      "indexes": {},
      "foreignKeys": {
        "workspace_members_user_id_users_id_fk": {
          "name": "workspace_members_user_id_users_id_fk",
          "tableFrom": "workspace_members",
          "tableTo": "users",
          "columnsFrom": [
            "user_id"
          ],
          "columnsTo": [
            "id"
          ],
          "onDelete": "cascade",
          "onUpdate": "no action"
        },
        "workspace_members_workspace_id_workspaces_id_fk": {
          "name": "workspace_members_workspace_id_workspaces_id_fk",
          "tableFrom": "workspace_members",
          "tableTo": "workspaces",
          "columnsFrom": [
            "workspace_id"
          ],
          "columnsTo": [
            "id"
          ],
          "onDelete": "cascade",
          "onUpdate": "no action"
        }
      },
      "compositePrimaryKeys": {
        "workspace_members_user_id_workspace_id_pk": {
          "name": "workspace_members_user_id_workspace_id_pk",
          "columns": [
            "user_id",
            "workspace_id"
          ]
        }
      },
      "uniqueConstraints": {},
      "policies": {},
      "checkConstraints": {},
      "isRLSEnabled": false
    },
    "public.workspaces": {
      "name": "workspaces",
      "schema": "",
      "columns": {
        "id": {
          "name": "id",
          "type": "text",
          "primaryKey": true,
          "notNull": true
        },
        "name": {
          "name": "name",
          "type": "text",
          "primaryKey": false,
          "notNull": true
        },
        "slug": {
          "name": "slug",
          "type": "text",
          "primaryKey": false,
          "notNull": true
        },
        "created_at": {
          "name": "created_at",
          "type": "timestamp",
          "primaryKey": false,
          "notNull": true,
          "default": "now()"
        }
      },
      "indexes": {},
      "foreignKeys": {},
      "compositePrimaryKeys": {},
      "uniqueConstraints": {
        "workspaces_slug_unique": {
          "name": "workspaces_slug_unique",
          "nullsNotDistinct": false,
          "columns": [
            "slug"
          ]
        }
      },
      "policies": {},
      "checkConstraints": {},
      "isRLSEnabled": false
    }
  },
  "enums": {
    "public.api_version_status": {
      "name": "api_version_status",
      "schema": "public",
      "values": [
        "active",
        "beta",
        "deprecated",
        "retired"
      ]
    },
    "public.doc_snippet_category": {
      "name": "doc_snippet_category",
      "schema": "public",
      "values": [
        "Structure",
        "Writing",
        "Data",
        "API"
      ]
    },
    "public.doc_status": {
      "name": "doc_status",
      "schema": "public",
      "values": [
        "draft",
        "review",
        "published",
        "archived"
      ]
    },
    "public.member_role": {
      "name": "member_role",
      "schema": "public",
      "values": [
        "owner",
        "editor",
        "viewer"
      ]
    },
    "public.openapi_source_type": {
      "name": "openapi_source_type",
      "schema": "public",
      "values": [
        "upload",
        "url"
      ]
    },
    "public.visibility_level": {
      "name": "visibility_level",
      "schema": "public",
      "values": [
        "public",
        "partner",
        "private"
      ]
    }
  },
  "schemas": {},
  "sequences": {},
  "roles": {},
  "policies": {},
  "views": {},
  "_meta": {
    "columns": {},
    "schemas": {},
    "tables": {}
  }
}